{
	"name": "master_ppl",
	"properties": {
		"activities": [
			{
				"name": "Execute Pipeline1",
				"type": "ExecutePipeline",
				"dependsOn": [],
				"policy": {
					"secureInput": false
				},
				"userProperties": [],
				"typeProperties": {
					"pipeline": {
						"referenceName": "chilld_ppl",
						"type": "PipelineReference"
					},
					"waitOnCompletion": true
				}
			}
		],
		"annotations": [],
		"lastPublishTime": "2024-06-16T13:27:54Z"
	},
	"type": "Microsoft.DataFactory/factories/pipelines"
}